<annotation>
	<folder>Opilo taeniatus</folder>
	<filename>20181225_162458.jpg</filename>
	<path>C:\Users\gokha\Desktop\DeepLearningPhotos\claridea_etiket\Opilo taeniatus\20181225_162458.jpg</path>
	<source>
		<database>Unknown</database>
	</source>
	<size>
		<width>3024</width>
		<height>4032</height>
		<depth>3</depth>
	</size>
	<segmented>0</segmented>
	<object>
		<name>opilo_taeniatus</name>
		<pose>Unspecified</pose>
		<truncated>0</truncated>
		<difficult>0</difficult>
		<bndbox>
			<xmin>567</xmin>
			<ymin>1528</ymin>
			<xmax>1751</xmax>
			<ymax>2474</ymax>
		</bndbox>
	</object>
</annotation>
