<annotation>
	<folder>murat</folder>
	<filename>murat52.jpg</filename>
	<path>/Users/mebpro-1/Desktop/model/murat/murat52.jpg</path>
	<source>
		<database>Unknown</database>
	</source>
	<size>
		<width>528</width>
		<height>396</height>
		<depth>3</depth>
	</size>
	<segmented>0</segmented>
	<object>
		<name>murat</name>
		<pose>Unspecified</pose>
		<truncated>0</truncated>
		<difficult>0</difficult>
		<bndbox>
			<xmin>38</xmin>
			<ymin>45</ymin>
			<xmax>454</xmax>
			<ymax>311</ymax>
		</bndbox>
	</object>
</annotation>
